LICENSE
README.md
pyproject.toml
openet/__init__.py
openet/geesebal/__init__.py
openet/geesebal/model.py
openet/geesebal/openet_collection.py
openet/geesebal/openet_image.py
openet/geesebal/openet_interpolate.py
openet/geesebal/openet_landsat.py
openet/geesebal/utils.py
openet/geesebal/tests/conftest.py
openet/geesebal/tests/test_a_utils.py
openet/geesebal/tests/test_b_landsat.py
openet/geesebal/tests/test_c_model.py
openet/geesebal/tests/test_d_openet_image.py
openet/geesebal/tests/test_e_openet_collection.py
openet/geesebal/tests/test_f_openet_interpolate.py
openet_geesebal.egg-info/PKG-INFO
openet_geesebal.egg-info/SOURCES.txt
openet_geesebal.egg-info/dependency_links.txt
openet_geesebal.egg-info/requires.txt
openet_geesebal.egg-info/top_level.txt