Metadata-Version: 2.1
Name: openet-geesebal
Version: 0.3.1
Summary: Earth Engine implementation of the GEESEBAL model
Author-email: Anderson Ruhoff <andersonruhoff@gmail.com>, Leonardo Laipelt <leolaipelt@gmail.com>, Bruno Comini <cominideandrade@gmail.com>
License: MIT License
Project-URL: Homepage, https://github.com/et-brasil/openet-geesebal
Keywords: GEESEBAL,OpenET,Earth Engine,Evapotranspiration,Landsat
Classifier: Programming Language :: Python :: 3
Classifier: License :: OSI Approved :: MIT License
Classifier: Operating System :: OS Independent
Requires-Python: >=3.8
License-File: LICENSE
Requires-Dist: earthengine-api>=0.1.367
Requires-Dist: openet-core>=0.4.0
Provides-Extra: test
Requires-Dist: pytest; extra == "test"
